nbgitpuller_link/__init__.py
nbgitpuller_link/_version.py
nbgitpuller_link/cli.py
nbgitpuller_link/link.py
nbgitpuller_link-0.2.5.dist-info/LICENSE.md
nbgitpuller_link-0.2.5.dist-info/METADATA
nbgitpuller_link-0.2.5.dist-info/WHEEL
nbgitpuller_link-0.2.5.dist-info/entry_points.txt
nbgitpuller_link-0.2.5.dist-info/top_level.txt
nbgitpuller_link-0.2.5.dist-info/RECORD
