Metadata-Version: 2.1
Name: nbgitpuller-link
Version: 0.2.5
Summary: Create an nbgitpuller link
Author-email: Mark Piper <mark.piper@colorado.edu>
Maintainer-email: Mark Piper <mark.piper@colorado.edu>
License: MIT License
Project-URL: Homepage, https://github.com/mdpiper/nbgitpuller-link
Project-URL: Documentation, https://github.com/mdpiper/nbgitpuller-link#readme
Project-URL: Repository, https://github.com/mdpiper/nbgitpuller-link
Project-URL: Changelog, https://github.com/mdpiper/nbgitpuller-link/blob/main/CHANGES.md
Keywords: jupyter,jupyterhub,notebook,git,nbgitpuller
Classifier: Programming Language :: Python :: 3
Classifier: Programming Language :: Python :: 3.10
Classifier: Programming Language :: Python :: 3.11
Classifier: Programming Language :: Python :: 3.12
Classifier: License :: OSI Approved :: MIT License
Classifier: Operating System :: OS Independent
Classifier: Intended Audience :: Developers
Classifier: Intended Audience :: Science/Research
Classifier: Intended Audience :: Education
Requires-Python: >=3.10
License-File: LICENSE.md
Requires-Dist: click
Requires-Dist: validators
Provides-Extra: build
Requires-Dist: build ; extra == 'build'
Requires-Dist: twine ; extra == 'build'
Requires-Dist: zest.releaser ; extra == 'build'
Provides-Extra: dev
Requires-Dist: black ; extra == 'dev'
Requires-Dist: flake8 ; extra == 'dev'
Requires-Dist: isort ; extra == 'dev'
Requires-Dist: nox ; extra == 'dev'
Provides-Extra: testing
Requires-Dist: pytest ; extra == 'testing'
Requires-Dist: pytest-cov ; extra == 'testing'
Requires-Dist: pytest-datadir ; extra == 'testing'
Requires-Dist: coveralls ; extra == 'testing'
